rpe/__init__.py
rpe/exceptions.py
rpe/policy.py
rpe/rpe.py
rpe/engines/__init__.py
rpe/engines/base.py
rpe/engines/opa.py
rpe/engines/python.py
rpe/extractors/__init__.py
rpe/extractors/gcp_auditlogs.py
rpe/extractors/micromanager.py
rpe/extractors/models.py
rpe/extractors/pubsub_metadata.py
rpe/resources/__init__.py
rpe/resources/base.py
rpe/resources/gcp.py
rpe_lib-3.2.1.dist-info/AUTHORS
rpe_lib-3.2.1.dist-info/LICENSE
rpe_lib-3.2.1.dist-info/METADATA
rpe_lib-3.2.1.dist-info/WHEEL
rpe_lib-3.2.1.dist-info/top_level.txt
rpe_lib-3.2.1.dist-info/RECORD
