Metadata-Version: 2.1
Name: rpe-lib
Version: 3.2.1
Summary: A resource policy evaluation library
Home-page: https://github.com/cleardataeng/resource-policy-evaluation-library
Author: Joe Ceresini
License: Apache 2.0
Keywords: gcp policy enforcement
Platform: UNKNOWN
Classifier: License :: OSI Approved :: Apache Software License
Classifier: Programming Language :: Python :: 3.7
Classifier: Programming Language :: Python :: 3.8
Requires-Dist: google-api-python-client
Requires-Dist: google-api-python-client-helpers
Requires-Dist: jmespath
Requires-Dist: tenacity
Requires-Dist: python-dateutil
